{
  "headwear": {
    "helmets": [
      {
        "name": "Bronze Helm",
        "jobs": [
          "Soldier",
          "Paladin",
          "Warrior",
          "Dragoon",
          "Defender",
          "Templar",
          "Mog Knight"
        ],
        "element": "None",
        "WpnATK": 0,
        "WpnDEF": 4,
        "MagPOW": 0,
        "MagRES": 2,
        "Speed": 0,
        "Move": 0,
        "Jump": 0,
        "Evade": 0,
        "description": "Helm of copper and leather.",
        "special_effects": null,
        "viera_only": false
      },
      {
        "name": "Iron Helm",
        "jobs": [
          "Soldier",
          "Paladin",
          "Warrior",
          "Dragoon",
          "Defender",
          "Templar",
          "Mog Knight"
        ],
        "element": "None",
        "WpnATK": 0,
        "WpnDEF": 5,
        "MagPOW": 0,
        "MagRES": 3,
        "Speed": 0,
        "Move": 0,
        "Jump": 0,
        "Evade": 0,
        "description": "Heavy, but very sturdy iron helmet.",
        "special_effects": null,
        "viera_only": false
      },
      {
        "name": "Opal Helm",
        "jobs": [
          "Soldier",
          "Paladin",
          "Warrior",
          "Dragoon",
          "Defender",
          "Templar",
          "Mog Knight"
        ],
        "element": "None",
        "WpnATK": 0,
        "WpnDEF": 7,
        "MagPOW": 0,
        "MagRES": 3,
        "Speed": 0,
        "Move": 0,
        "Jump": 0,
        "Evade": 0,
        "description": "Formal helm worn in ceremonies.",
        "special_effects": null,
        "viera_only": false
      },
      {
        "name": "Cross Helm",
        "jobs": [
          "Soldier",
          "Paladin",
          "Warrior",
          "Dragoon",
          "Defender",
          "Templar",
          "Mog Knight"
        ],
        "element": "None",
        "WpnATK": 0,
        "WpnDEF": 9,
        "MagPOW": 0,
        "MagRES": 4,
        "Speed": 0,
        "Move": 0,
        "Jump": 0,
        "Evade": 0,
        "description": "This helmet is made to cover the whole face.",
        "special_effects": null,
        "viera_only": false
      },
      {
        "name": "Diamond Helm",
        "jobs": [
          "Soldier",
          "Paladin",
          "Warrior",
          "Dragoon",
          "Defender",
          "Templar",
          "Mog Knight"
        ],
        "element": "None",
        "WpnATK": 0,
        "WpnDEF": 11,
        "MagPOW": 0,
        "MagRES": 5,
        "Speed": 0,
        "Move": 0,
        "Jump": 0,
        "Evade": 0,
        "description": "This helmet is pricey but very reliable.",
        "special_effects": null,
        "viera_only": false
      },
      {
        "name": "Parade Helm",
        "jobs": [
          "Soldier",
          "Paladin",
          "Warrior",
          "Dragoon",
          "Defender",
          "Templar",
          "Mog Knight"
        ],
        "element": "None",
        "WpnATK": 0,
        "WpnDEF": 13,
        "MagPOW": 0,
        "MagRES": 4,
        "Speed": 0,
        "Move": 0,
        "Jump": 0,
        "Evade": 0,
        "description": "Helm with a large crimson plume. Used in ceremonies.",
        "special_effects": null,
        "viera_only": false
      },
      {
        "name": "Hanya Helm",
        "jobs": [
          "Soldier",
          "Paladin",
          "Warrior",
          "Dragoon",
          "Defender",
          "Templar",
          "Mog Knight"
        ],
        "element": "None",
        "WpnATK": 0,
        "WpnDEF": 12,
        "MagPOW": 0,
        "MagRES": 8,
        "Speed": 0,
        "Move": 0,
        "Jump": 0,
        "Evade": 0,
        "description": "Frightful helm in the shape of a demon.",
        "special_effects": null,
        "viera_only": false
      },
      {
        "name": "Bangaa Helm",
        "jobs": [
          "Soldier",
          "Paladin",
          "Warrior",
          "Dragoon",
          "Defender",
          "Templar",
          "Mog Knight"
        ],
        "element": "None",
        "WpnATK": 0,
        "WpnDEF": 16,
        "MagPOW": 0,
        "MagRES": 6,
        "Speed": 0,
        "Move": 0,
        "Jump": 0,
        "Evade": 0,
        "description": "Strong and sturdy helmet used by bangaa.",
        "special_effects": null,
        "viera_only": false
      }
    ],
    "ribbons": [
      {
        "name": "Cachusha",
        "jobs": [
          "Fencer",
          "Elementalist",
          "Red Mage",
          "White Mage",
          "Summoner",
          "Archer",
          "Assassain",
          "Sniper"
        ],
        "element": "None",
        "WpnATK": 0,
        "WpnDEF": 2,
        "MagPOW": 0,
        "MagRES": 5,
        "Speed": 0,
        "Move": 0,
        "Jump": 0,
        "Evade": 0,
        "description": "Words of blessing adorn this red women's ornament.",
        "special_effects": {
          "Null": [
            "KO",
            "Petrify",
            "Confuse",
            "Berserk",
            "Stop",
            "Charm",
            "Sleep"
          ]
        },
        "viera_only": true
      },
      {
        "name": "Barette",
        "jobs": [
          "Fencer",
          "Elementalist",
          "Red Mage",
          "White Mage",
          "Summoner",
          "Archer",
          "Assassain",
          "Sniper"
        ],
        "element": "None",
        "WpnATK": 0,
        "WpnDEF": 2,
        "MagPOW": 0,
        "MagRES": 5,
        "Speed": 0,
        "Move": 0,
        "Jump": 0,
        "Evade": 0,
        "description": "Women's hairpin adorned with good luck stones.",
        "special_effects": {
          "Null": [
            "Zombie",
            "Dark",
            "Silence",
            "Frog",
            "Poison",
            "Slow",
            "Immobilize",
            "Disable",
            "Doom"
          ]
        },
        "viera_only": true
      },
      {
        "name": "Ribbon",
        "jobs": [
          "Fencer",
          "Elementalist",
          "Red Mage",
          "White Mage",
          "Summoner",
          "Archer",
          "Assassain",
          "Sniper"
        ],
        "element": "None",
        "WpnATK": 0,
        "WpnDEF": 2,
        "MagPOW": 0,
        "MagRES": 5,
        "Speed": 0,
        "Move": 0,
        "Jump": 0,
        "Evade": 0,
        "description": "This women's ribbon wards off all ailment.",
        "special_effects": {
          "Null": [
            "all"
          ]
        },
        "viera_only": true
      }
    ],
    "hats": [
      {
        "name": "Feather Cap",
        "jobs": [
          "Soldier",
          "Fighter",
          "Thief",
          "Ninja",
          "White Mage",
          "Black Mage",
          "IllusionistBlue Mage",
          "Archer",
          "Hunter",
          "Warrior",
          "Gladiator",
          "Bishop",
          "Templar",
          "Time Mage",
          "Alchemist",
          "Beastmaster",
          "Morpher",
          "Sage",
          "Fencer",
          "Elementalist",
          "Red Mage",
          "Summoner",
          "Assassain",
          "Sniper",
          "Animist",
          "Gunner",
          "Juggler",
          "Gadgeteer"
        ],
        "element": "None",
        "WpnATK": 0,
        "WpnDEF": 2,
        "MagPOW": 0,
        "MagRES": 4,
        "Speed": 0,
        "Move": 0,
        "Jump": 0,
        "Evade": 0,
        "description": "Sturdy cap with a long feather.",
        "special_effects": null,
        "viera_only": false
      },
      {
        "name": "Circlet",
        "jobs": [
          "Soldier",
          "Fighter",
          "Thief",
          "Ninja",
          "White Mage",
          "Black Mage",
          "Illusionist",
          "Blue Mage",
          "Archer",
          "Hunter",
          "Warrior",
          "Gladiator",
          "Bishop",
          "Templar",
          "Time Mage",
          "Alchemist",
          "Beastmaster",
          "Morpher",
          "Sage",
          "Fencer",
          "Elementalist",
          "Red Mage",
          "Summoner",
          "Assassain",
          "Sniper",
          "Animist",
          "Gunner",
          "Juggler",
          "Gadgeteer"
        ],
        "element": "None",
        "WpnATK": 0,
        "WpnDEF": 3,
        "MagPOW": 0,
        "MagRES": 3,
        "Speed": 0,
        "Move": 0,
        "Jump": 0,
        "Evade": 0,
        "description": "Ornament meant to protect wearer from harmful magic.",
        "special_effects": null,
        "viera_only": false
      },
      {
        "name": "Green Baret",
        "jobs": [
          "Soldier",
          "Fighter",
          "Thief",
          "Ninja",
          "White Mage",
          "Black Mage",
          "Illusionist",
          "Blue Mage",
          "Archer",
          "Hunter",
          "Warrior",
          "Gladiator",
          "Bishop",
          "Templar",
          "Time Mage",
          "Alchemist",
          "Beastmaster",
          "Morpher",
          "Sage",
          "Fencer",
          "Elementalist",
          "Red Mage",
          "Summoner",
          "Assassain",
          "Sniper",
          "Animist",
          "Gunner",
          "Juggler",
          "Gadgeteer"
        ],
        "element": "None",
        "WpnATK": 0,
        "WpnDEF": 2,
        "MagPOW": 0,
        "MagRES": 2,
        "Speed": 0,
        "Move": 0,
        "Jump": 0,
        "Evade": 2,
        "description": "This hat is given to those with a special mission.",
        "special_effects": null,
        "viera_only": false
      },
      {
        "name": "Headband",
        "jobs": [
          "Soldier",
          "Fighter",
          "Thief",
          "Ninja",
          "White Mage",
          "Black Mage",
          "IllusionistBlue Mage",
          "Archer",
          "Hunter",
          "Warrior",
          "Gladiator",
          "Bishop",
          "Templar",
          "Time Mage",
          "Alchemist",
          "Beastmaster",
          "Morpher",
          "Sage",
          "Fencer",
          "Elementalist",
          "Red Mage",
          "Summoner",
          "Assassain",
          "Sniper",
          "Animist",
          "Gunner",
          "Juggler",
          "Gadgeteer"
        ],
        "element": "None",
        "WpnATK": 5,
        "WpnDEF": 6,
        "MagPOW": 0,
        "MagRES": 2,
        "Speed": 0,
        "Move": 0,
        "Jump": 0,
        "Evade": 0,
        "description": "This headband serves to focus the spirit.",
        "special_effects": null,
        "viera_only": false
      },
      {
        "name": "Wizard Hat",
        "jobs": [
          "Soldier",
          "Fighter",
          "Thief",
          "Ninja",
          "White Mage",
          "Black Mage",
          "IllusionistBlue Mage",
          "Archer",
          "Hunter",
          "Warrior",
          "Gladiator",
          "Bishop",
          "Templar",
          "Time Mage",
          "Alchemist",
          "Beastmaster",
          "Morpher",
          "Sage",
          "Fencer",
          "Elementalist",
          "Red Mage",
          "Summoner",
          "Assassain",
          "Sniper",
          "Animist",
          "Gunner",
          "Juggler",
          "Gadgeteer"
        ],
        "element": "None",
        "WpnATK": 0,
        "WpnDEF": 3,
        "MagPOW": 1,
        "MagRES": 10,
        "Speed": 0,
        "Move": 0,
        "Jump": 0,
        "Evade": 0,
        "description": "This pointed cap is a classic wizard's hat.",
        "special_effects": null,
        "viera_only": false
      },
      {
        "name": "Gold Hairpin",
        "jobs": [
          "Soldier",
          "Fighter",
          "Thief",
          "Ninja",
          "White Mage",
          "Black Mage",
          "IllusionistBlue Mage",
          "Archer",
          "Hunter",
          "Warrior",
          "Gladiator",
          "Bishop",
          "Templar",
          "Time Mage",
          "Alchemist",
          "Beastmaster",
          "Morpher",
          "Sage",
          "Fencer",
          "Elementalist",
          "Red Mage",
          "Summoner",
          "Assassain",
          "Sniper",
          "Animist",
          "Gunner",
          "Juggler",
          "Gadgeteer"
        ],
        "element": "None",
        "WpnATK": 0,
        "WpnDEF": 4,
        "MagPOW": 2,
        "MagRES": 12,
        "Speed": 0,
        "Move": 0,
        "Jump": 0,
        "Evade": 0,
        "description": "Hairpin with fine gold-work. Made by a sorceress.",
        "special_effects": {
          "Null": [
            "Silence"
          ]
        },
        "viera_only": false
      },
      {
        "name": "Thief Hat",
        "jobs": [
          "Soldier",
          "Fighter",
          "Thief",
          "Ninja",
          "White Mage",
          "Black Mage",
          "IllusionistBlue Mage",
          "Archer",
          "Hunter",
          "Warrior",
          "Gladiator",
          "Bishop",
          "Templar",
          "Time Mage",
          "Alchemist",
          "Beastmaster",
          "Morpher",
          "Sage",
          "Fencer",
          "Elementalist",
          "Red Mage",
          "Summoner",
          "Assassain",
          "Sniper",
          "Animist",
          "Gunner",
          "Juggler",
          "Gadgeteer"
        ],
        "element": "None",
        "WpnATK": 0,
        "WpnDEF": 8,
        "MagPOW": 0,
        "MagRES": 6,
        "Speed": 0,
        "Move": 0,
        "Jump": 0,
        "Evade": 7,
        "description": "Hat said to have belonged to a notorious thief.",
        "special_effects": {
          "Null": [
            "Immobilize",
            "Disable"
          ]
        },
        "viera_only": false
      },
      {
        "name": "Black Hat",
        "jobs": [
          "Soldier",
          "Fighter",
          "Thief",
          "Ninja",
          "White Mage",
          "Black Mage",
          "IllusionistBlue Mage",
          "Archer",
          "Hunter",
          "Warrior",
          "Gladiator",
          "Bishop",
          "Templar",
          "Time Mage",
          "Alchemist",
          "Beastmaster",
          "Morpher",
          "Sage",
          "Fencer",
          "Elementalist",
          "Red Mage",
          "Summoner",
          "Assassain",
          "Sniper",
          "Animist",
          "Gunner",
          "Juggler",
          "Gadgeteer"
        ],
        "element": "None",
        "WpnATK": 0,
        "WpnDEF": 4,
        "MagPOW": 4,
        "MagRES": 16,
        "Speed": 0,
        "Move": 0,
        "Jump": 0,
        "Evade": 0,
        "description": "Black pointy hat made of magical thread.",
        "special_effects": null,
        "viera_only": false
      },
      {
        "name": "White Hat",
        "jobs": [
          "Soldier",
          "Fighter",
          "Thief",
          "Ninja",
          "White Mage",
          "Black Mage",
          "IllusionistBlue Mage",
          "Archer",
          "Hunter",
          "Warrior",
          "Gladiator",
          "Bishop",
          "Templar",
          "Time Mage",
          "Alchemist",
          "Beastmaster",
          "Morpher",
          "Sage",
          "Fencer",
          "Elementalist",
          "Red Mage",
          "Summoner",
          "Assassain",
          "Sniper",
          "Animist",
          "Gunner",
          "Juggler",
          "Gadgeteer"
        ],
        "element": "None",
        "WpnATK": 0,
        "WpnDEF": 4,
        "MagPOW": 0,
        "MagRES": 14,
        "Speed": 0,
        "Move": 0,
        "Jump": 0,
        "Evade": 0,
        "description": "White hat with furry ears. Made of magical thread.",
        "special_effects": null,
        "viera_only": false
      },
      {
        "name": "Acacia Hat",
        "jobs": [
          "Soldier",
          "Fighter",
          "Thief",
          "Ninja",
          "White Mage",
          "Black Mage",
          "IllusionistBlue Mage",
          "Archer",
          "Hunter",
          "Warrior",
          "Gladiator",
          "Bishop",
          "Templar",
          "Time Mage",
          "Alchemist",
          "Beastmaster",
          "Morpher",
          "Sage",
          "Fencer",
          "Elementalist",
          "Red Mage",
          "Summoner",
          "Assassain",
          "Sniper",
          "Animist",
          "Gunner",
          "Juggler",
          "Gadgeteer"
        ],
        "element": "None",
        "WpnATK": 0,
        "WpnDEF": 2,
        "MagPOW": 5,
        "MagRES": 2,
        "Speed": 2,
        "Move": 1,
        "Jump": 1,
        "Evade": 5,
        "description": "Odd, light yellow hat that grows with its wearer.",
        "special_effects": null,
        "viera_only": false
      },
      {
        "name": "Tiara",
        "jobs": [
          "Soldier",
          "Fighter",
          "Thief",
          "Ninja",
          "White Mage",
          "Black Mage",
          "IllusionistBlue Mage",
          "Archer",
          "Hunter",
          "Warrior",
          "Gladiator",
          "Bishop",
          "Templar",
          "Time Mage",
          "Alchemist",
          "Beastmaster",
          "Morpher",
          "Sage",
          "Fencer",
          "Elementalist",
          "Red Mage",
          "Summoner",
          "Assassain",
          "Sniper",
          "Animist",
          "Gunner",
          "Juggler",
          "Gadgeteer"
        ],
        "element": "None",
        "WpnATK": 0,
        "WpnDEF": 8,
        "MagPOW": 0,
        "MagRES": 20,
        "Speed": 0,
        "Move": 0,
        "Jump": 0,
        "Evade": 0,
        "description": "Gift Tiara given to the most beautiful women.",
        "special_effects": null,
        "viera_only": false
      }
    ]
  },
  "armor": {
    "armor": [
      {
        "name": "Cuirass",
        "jobs": [
          "Soldier",
          "Paladin",
          "Warrior",
          "Dragoon",
          "Defender",
          "Templar Mog Knight"
        ],
        "element": "None",
        "WpnATK": 0,
        "WpnDEF": 28,
        "MagPOW": 0,
        "MagRES": 2,
        "Speed": 0,
        "Move": 0,
        "Jump": 0,
        "Evade": 0,
        "description": "Chestplate made of tightly woven fibers.",
        "special_effects": null,
        "viera_only": false
      },
      {
        "name": "Bronze Armor",
        "jobs": [
          "Soldier",
          "Paladin",
          "Warrior",
          "Dragoon",
          "Defender",
          "Templar Mog Knight"
        ],
        "element": "None",
        "WpnATK": 0,
        "WpnDEF": 30,
        "MagPOW": 0,
        "MagRES": 6,
        "Speed": 0,
        "Move": 0,
        "Jump": 0,
        "Evade": 0,
        "description": "Armor made of intertwined copper plates.",
        "special_effects": null,
        "viera_only": false
      },
      {
        "name": "Iron Armor",
        "jobs": [
          "Soldier",
          "Paladin",
          "Warrior",
          "Dragoon",
          "Defender",
          "Templar Mog Knight"
        ],
        "element": "None",
        "WpnATK": 0,
        "WpnDEF": 34,
        "MagPOW": 0,
        "MagRES": 3,
        "Speed": 0,
        "Move": 0,
        "Jump": 0,
        "Evade": 0,
        "description": "Heavy armor with steel on the chest.",
        "special_effects": null,
        "viera_only": false
      },
      {
        "name": "Gold Armor",
        "jobs": [
          "Soldier",
          "Paladin",
          "Warrior",
          "Dragoon",
          "Defender",
          "Templar Mog Knight"
        ],
        "element": "None",
        "WpnATK": 0,
        "WpnDEF": 42,
        "MagPOW": 0,
        "MagRES": 6,
        "Speed": 0,
        "Move": 0,
        "Jump": 0,
        "Evade": 0,
        "description": "Expensive armor plated in gold.",
        "special_effects": null,
        "viera_only": false
      },
      {
        "name": "Diamond Armor",
        "jobs": [
          "Soldier",
          "Paladin",
          "Warrior",
          "Dragoon",
          "Defender",
          "Templar Mog Knight"
        ],
        "element": "None",
        "WpnATK": 0,
        "WpnDEF": 40,
        "MagPOW": 0,
        "MagRES": 3,
        "Speed": 0,
        "Move": 0,
        "Jump": 0,
        "Evade": 0,
        "description": "This armor is set with sparkling diamonds.",
        "special_effects": null,
        "viera_only": false
      },
      {
        "name": "Opal Armor",
        "jobs": [
          "Soldier",
          "Paladin",
          "Warrior",
          "Dragoon",
          "Defender",
          "Templar Mog Knight"
        ],
        "element": "None",
        "WpnATK": 0,
        "WpnDEF": 42,
        "MagPOW": 0,
        "MagRES": 3,
        "Speed": 0,
        "Move": 0,
        "Jump": 0,
        "Evade": 0,
        "description": "Beautiful armor with exquisite curves.",
        "special_effects": null,
        "viera_only": false
      },
      {
        "name": "Carabini Mail",
        "jobs": [
          "Soldier",
          "Paladin",
          "Warrior",
          "Dragoon",
          "Defender",
          "Templar Mog Knight"
        ],
        "element": "None",
        "WpnATK": 0,
        "WpnDEF": 38,
        "MagPOW": 0,
        "MagRES": 8,
        "Speed": 0,
        "Move": 0,
        "Jump": 0,
        "Evade": 0,
        "description": "Light armor made of iron fused with mythril.",
        "special_effects": null,
        "viera_only": false
      },
      {
        "name": "Mirror Mail",
        "jobs": [
          "Soldier",
          "Paladin",
          "Warrior",
          "Dragoon",
          "Defender",
          "Templar Mog Knight"
        ],
        "element": "None",
        "WpnATK": 0,
        "WpnDEF": 36,
        "MagPOW": 0,
        "MagRES": 8,
        "Speed": 0,
        "Move": 0,
        "Jump": 0,
        "Evade": 0,
        "description": "Lighter armor imbued with a magical reflection aura.",
        "special_effects": null,
        "viera_only": false
      },
      {
        "name": "Dragon Mail",
        "jobs": [
          "Soldier",
          "Paladin",
          "Warrior",
          "Dragoon",
          "Defender",
          "Templar Mog Knight"
        ],
        "element": "None",
        "WpnATK": 0,
        "WpnDEF": 40,
        "MagPOW": 0,
        "MagRES": 8,
        "Speed": 0,
        "Move": 0,
        "Jump": 0,
        "Evade": 0,
        "description": "Armor made of metal fused with dragon scales.",
        "special_effects": {
          "Half": [
            "Fire"
          ]
        },
        "viera_only": false
      },
      {
        "name": "Genji Armor",
        "jobs": [
          "Soldier",
          "Paladin",
          "Warrior",
          "Dragoon",
          "Defender",
          "Templar Mog Knight"
        ],
        "element": "None",
        "WpnATK": 0,
        "WpnDEF": 46,
        "MagPOW": 0,
        "MagRES": 12,
        "Speed": 0,
        "Move": 0,
        "Jump": 0,
        "Evade": 0,
        "description": "One-of-a-kind armor from a foreign land.",
        "special_effects": null,
        "viera_only": false
      },
      {
        "name": "Maximillian",
        "jobs": [
          "Soldier",
          "Paladin",
          "Warrior",
          "Dragoon",
          "Defender",
          "Templar Mog Knight"
        ],
        "element": "None",
        "WpnATK": 3,
        "WpnDEF": 46,
        "MagPOW": 0,
        "MagRES": 10,
        "Speed": 0,
        "Move": 0,
        "Jump": 0,
        "Evade": 0,
        "description": "This armor bears the crest of \"The Last Knight.\"",
        "special_effects": null,
        "viera_only": false
      },
      {
        "name": "Adaman Armor",
        "jobs": [
          "Soldier",
          "Paladin",
          "Warrior",
          "Dragoon",
          "Defender",
          "Templar Mog Knight"
        ],
        "element": "None",
        "WpnATK": 0,
        "WpnDEF": 58,
        "MagPOW": 0,
        "MagRES": 3,
        "Speed": 0,
        "Move": 0,
        "Jump": 0,
        "Evade": 0,
        "description": "Armor of beautifully tempered green adamantite.",
        "special_effects": null,
        "viera_only": false
      },
      {
        "name": "Materia Armor",
        "jobs": [
          "Soldier",
          "Paladin",
          "Warrior",
          "Dragoon",
          "Defender",
          "Templar Mog Knight"
        ],
        "element": "None",
        "WpnATK": 0,
        "WpnDEF": 52,
        "MagPOW": 0,
        "MagRES": 16,
        "Speed": 0,
        "Move": 0,
        "Jump": 0,
        "Evade": 0,
        "description": "Extremely hard armor made of materite.",
        "special_effects": null,
        "viera_only": false
      },
      {
        "name": "Peytral",
        "jobs": [
          "Soldier",
          "Paladin",
          "Warrior",
          "Dragoon",
          "Defender",
          "Templar Mog Knight"
        ],
        "element": "None",
        "WpnATK": 5,
        "WpnDEF": 29,
        "MagPOW": 5,
        "MagRES": 2,
        "Speed": 2,
        "Move": 1,
        "Jump": 1,
        "Evade": 5,
        "description": "Heavy, but sturdy armor. Made for war chocobo use.",
        "special_effects": null,
        "viera_only": false
      }
    ],
    "clothing": [
      {
        "name": "Leather Garb",
        "jobs": [
          "Soldier",
          "Fighter",
          "Thief",
          "Ninja",
          "White Mage",
          "Black Mage",
          "IllusionistBlue Mage Archer",
          "Hunter",
          "Warrior",
          "Gladiator",
          "White Monk",
          "Bishop",
          "Templar",
          "Time Mage",
          "Alchemist",
          "Beastmaster",
          "Morpher",
          "Sage",
          "Fencer",
          "Elementalist",
          "Red Mage",
          "Summoner",
          "Assassain",
          "Sniper",
          "Animist",
          "Gunner",
          "Juggler",
          "Gadgeteer"
        ],
        "element": "None",
        "WpnATK": 0,
        "WpnDEF": 18,
        "MagPOW": 0,
        "MagRES": 4,
        "Speed": 0,
        "Move": 0,
        "Jump": 0,
        "Evade": 0,
        "description": "Sturdy clothing made of layered leather.",
        "special_effects": null,
        "viera_only": false
      },
      {
        "name": "Chain Plate",
        "jobs": [
          "Soldier",
          "Fighter",
          "Thief",
          "Ninja",
          "White Mage",
          "Black Mage",
          "IllusionistBlue Mage Archer",
          "Hunter",
          "Warrior",
          "Gladiator",
          "White Monk",
          "Bishop",
          "Templar",
          "Time Mage",
          "Alchemist",
          "Beastmaster",
          "Morpher",
          "Sage",
          "Fencer",
          "Elementalist",
          "Red Mage",
          "Summoner",
          "Assassain",
          "Sniper",
          "Animist",
          "Gunner",
          "Juggler",
          "Gadgeteer"
        ],
        "element": "None",
        "WpnATK": 0,
        "WpnDEF": 28,
        "MagPOW": 0,
        "MagRES": 4,
        "Speed": 0,
        "Move": 0,
        "Jump": 0,
        "Evade": 0,
        "description": "Shirt of linked iron rings",
        "special_effects": null,
        "viera_only": false
      },
      {
        "name": "Adaman Vest",
        "jobs": [
          "Soldier",
          "Fighter",
          "Thief",
          "Ninja",
          "White Mage",
          "Black Mage",
          "IllusionistBlue Mage Archer",
          "Hunter",
          "Warrior",
          "Gladiator",
          "White Monk",
          "Bishop",
          "Templar",
          "Time Mage",
          "Alchemist",
          "Beastmaster",
          "Morpher",
          "Sage",
          "Fencer",
          "Elementalist",
          "Red Mage",
          "Summoner",
          "Assassain",
          "Sniper",
          "Animist",
          "Gunner",
          "Juggler",
          "Gadgeteer"
        ],
        "element": "None",
        "WpnATK": 0,
        "WpnDEF": 30,
        "MagPOW": 0,
        "MagRES": 3,
        "Speed": 0,
        "Move": 0,
        "Jump": 0,
        "Evade": 0,
        "description": "Shirt woven of adamantite alloy.",
        "special_effects": null,
        "viera_only": false
      },
      {
        "name": "Survival Vest",
        "jobs": [
          "Soldier",
          "Fighter",
          "Thief",
          "Ninja",
          "White Mage",
          "Black Mage",
          "IllusionistBlue Mage Archer",
          "Hunter",
          "Warrior",
          "Gladiator",
          "White Monk",
          "Bishop",
          "Templar",
          "Time Mage",
          "Alchemist",
          "Beastmaster",
          "Morpher",
          "Sage",
          "Fencer",
          "Elementalist",
          "Red Mage",
          "Summoner",
          "Assassain",
          "Sniper",
          "Animist",
          "Gunner",
          "Juggler",
          "Gadgeteer"
        ],
        "element": "None",
        "WpnATK": 0,
        "WpnDEF": 34,
        "MagPOW": 0,
        "MagRES": 6,
        "Speed": 0,
        "Move": 0,
        "Jump": 0,
        "Evade": 0,
        "description": "Light cotton wear for absorbing shocks.",
        "special_effects": null,
        "viera_only": false
      },
      {
        "name": "Brigandine",
        "jobs": [
          "Soldier",
          "Fighter",
          "Thief",
          "Ninja",
          "White Mage",
          "Black Mage",
          "IllusionistBlue Mage Archer",
          "Hunter",
          "Warrior",
          "Gladiator",
          "White Monk",
          "Bishop",
          "Templar",
          "Time Mage",
          "Alchemist",
          "Beastmaster",
          "Morpher",
          "Sage",
          "Fencer",
          "Elementalist",
          "Red Mage",
          "Summoner",
          "Assassain",
          "Sniper",
          "Animist",
          "Gunner",
          "Juggler",
          "Gadgeteer"
        ],
        "element": "None",
        "WpnATK": 0,
        "WpnDEF": 37,
        "MagPOW": 0,
        "MagRES": 6,
        "Speed": 0,
        "Move": 0,
        "Jump": 0,
        "Evade": 0,
        "description": "Clothes made so the metal strips won't rub together.",
        "special_effects": null,
        "viera_only": false
      },
      {
        "name": "Judo Uniform",
        "jobs": [
          "Soldier",
          "Fighter",
          "Thief",
          "Ninja",
          "White Mage",
          "Black Mage",
          "IllusionistBlue Mage Archer",
          "Hunter",
          "Warrior",
          "Gladiator",
          "White Monk",
          "Bishop",
          "Templar",
          "Time Mage",
          "Alchemist",
          "Beastmaster",
          "Morpher",
          "Sage",
          "Fencer",
          "Elementalist",
          "Red Mage",
          "Summoner",
          "Assassain",
          "Sniper",
          "Animist",
          "Gunner",
          "Juggler",
          "Gadgeteer"
        ],
        "element": "None",
        "WpnATK": 0,
        "WpnDEF": 34,
        "MagPOW": 0,
        "MagRES": 8,
        "Speed": 0,
        "Move": 0,
        "Jump": 0,
        "Evade": 0,
        "description": "Fighting clothes perferred by monks.",
        "special_effects": {
          "Null": [
            "Doom"
          ]
        },
        "viera_only": false
      },
      {
        "name": "Power Sash",
        "jobs": [
          "Soldier",
          "Fighter",
          "Thief",
          "Ninja",
          "White Mage",
          "Black Mage",
          "IllusionistBlue Mage Archer",
          "Hunter",
          "Warrior",
          "Gladiator",
          "White Monk",
          "Bishop",
          "Templar",
          "Time Mage",
          "Alchemist",
          "Beastmaster",
          "Morpher",
          "Sage",
          "Fencer",
          "Elementalist",
          "Red Mage",
          "Summoner",
          "Assassain",
          "Sniper",
          "Animist",
          "Gunner",
          "Juggler",
          "Gadgeteer"
        ],
        "element": "None",
        "WpnATK": 2,
        "WpnDEF": 34,
        "MagPOW": 0,
        "MagRES": 10,
        "Speed": 0,
        "Move": 0,
        "Jump": 0,
        "Evade": 0,
        "description": "Twisted rope used for tying back loose clothing.",
        "special_effects": null,
        "viera_only": false
      },
      {
        "name": "Gaia Gear",
        "jobs": [
          "Soldier",
          "Fighter",
          "Thief",
          "Ninja",
          "White Mage",
          "Black Mage",
          "IllusionistBlue Mage Archer",
          "Hunter",
          "Warrior",
          "Gladiator",
          "White Monk",
          "Bishop",
          "Templar",
          "Time Mage",
          "Alchemist",
          "Beastmaster",
          "Morpher",
          "Sage",
          "Fencer",
          "Elementalist",
          "Red Mage",
          "Summoner",
          "Assassain",
          "Sniper",
          "Animist",
          "Gunner",
          "Juggler",
          "Gadgeteer"
        ],
        "element": "Earth",
        "WpnATK": 0,
        "WpnDEF": 24,
        "MagPOW": 0,
        "MagRES": 12,
        "Speed": 0,
        "Move": 0,
        "Jump": 0,
        "Evade": 0,
        "description": "These blue clothes have been blessed by the earth.",
        "special_effects": {
          "Absb": [
            "Earth"
          ]
        },
        "viera_only": false
      },
      {
        "name": "Ninja Gear",
        "jobs": [
          "Soldier",
          "Fighter",
          "Thief",
          "Ninja",
          "White Mage",
          "Black Mage",
          "IllusionistBlue Mage Archer",
          "Hunter",
          "Warrior",
          "Gladiator",
          "White Monk",
          "Bishop",
          "Templar",
          "Time Mage",
          "Alchemist",
          "Beastmaster",
          "Morpher",
          "Sage",
          "Fencer",
          "Elementalist",
          "Red Mage",
          "Summoner",
          "Assassain",
          "Sniper",
          "Animist",
          "Gunner",
          "Juggler",
          "Gadgeteer"
        ],
        "element": "None",
        "WpnATK": 0,
        "WpnDEF": 30,
        "MagPOW": 0,
        "MagRES": 6,
        "Speed": 1,
        "Move": 0,
        "Jump": 0,
        "Evade": 2,
        "description": "Ninja clothes made using special secret techniques.",
        "special_effects": null,
        "viera_only": false
      },
      {
        "name": "Dark Gear",
        "jobs": [
          "Soldier",
          "Fighter",
          "Thief",
          "Ninja",
          "White Mage",
          "Black Mage",
          "IllusionistBlue Mage Archer",
          "Hunter",
          "Warrior",
          "Gladiator",
          "White Monk",
          "Bishop",
          "Templar",
          "Time Mage",
          "Alchemist",
          "Beastmaster",
          "Morpher",
          "Sage",
          "Fencer",
          "Elementalist",
          "Red Mage",
          "Summoner",
          "Assassain",
          "Sniper",
          "Animist",
          "Gunner",
          "Juggler",
          "Gadgeteer"
        ],
        "element": "None",
        "WpnATK": 0,
        "WpnDEF": 32,
        "MagPOW": 0,
        "MagRES": 3,
        "Speed": 2,
        "Move": 0,
        "Jump": 0,
        "Evade": 1,
        "description": "Black clothes used for night operations.",
        "special_effects": {
          "Null": [
            "Stop"
          ]
        },
        "viera_only": false
      },
      {
        "name": "Wygar",
        "jobs": [
          "Soldier",
          "Fighter",
          "Thief",
          "Ninja",
          "White Mage",
          "Black Mage",
          "IllusionistBlue Mage Archer",
          "Hunter",
          "Warrior",
          "Gladiator",
          "White Monk",
          "Bishop",
          "Templar",
          "Time Mage",
          "Alchemist",
          "Beastmaster",
          "Morpher",
          "Sage",
          "Fencer",
          "Elementalist",
          "Red Mage",
          "Summoner",
          "Assassain",
          "Sniper",
          "Animist",
          "Gunner",
          "Juggler",
          "Gadgeteer"
        ],
        "element": "None",
        "WpnATK": 0,
        "WpnDEF": 35,
        "MagPOW": 0,
        "MagRES": 10,
        "Speed": 0,
        "Move": 0,
        "Jump": 0,
        "Evade": 0,
        "description": "Clothes worn by an ancient hero king.",
        "special_effects": {
          "Null": [
            "KO"
          ]
        },
        "viera_only": false
      },
      {
        "name": "Mirage Vest",
        "jobs": [
          "Soldier",
          "Fighter",
          "Thief",
          "Ninja",
          "White Mage",
          "Black Mage",
          "IllusionistBlue Mage Archer",
          "Hunter",
          "Warrior",
          "Gladiator",
          "White Monk",
          "Bishop",
          "Templar",
          "Time Mage",
          "Alchemist",
          "Beastmaster",
          "Morpher",
          "Sage",
          "Fencer",
          "Elementalist",
          "Red Mage",
          "Summoner",
          "Assassain",
          "Sniper",
          "Animist",
          "Gunner",
          "Juggler",
          "Gadgeteer"
        ],
        "element": "Holy",
        "WpnATK": 0,
        "WpnDEF": 32,
        "MagPOW": 0,
        "MagRES": 16,
        "Speed": 0,
        "Move": 0,
        "Jump": 0,
        "Evade": 0,
        "description": "These clothes shimmer mystically in the light.",
        "special_effects": null,
        "viera_only": false
      },
      {
        "name": "Bone Plate",
        "jobs": [
          "Soldier",
          "Fighter",
          "Thief",
          "Ninja",
          "White Mage",
          "Black Mage",
          "IllusionistBlue Mage Archer",
          "Hunter",
          "Warrior",
          "Gladiator",
          "White Monk",
          "Bishop",
          "Templar",
          "Time Mage",
          "Alchemist",
          "Beastmaster",
          "Morpher",
          "Sage",
          "Fencer",
          "Elementalist",
          "Red Mage",
          "Summoner",
          "Assassain",
          "Sniper",
          "Animist",
          "Gunner",
          "Juggler",
          "Gadgeteer"
        ],
        "element": "Dark",
        "WpnATK": 0,
        "WpnDEF": 42,
        "MagPOW": 0,
        "MagRES": 8,
        "Speed": 0,
        "Move": 0,
        "Jump": 0,
        "Evade": 0,
        "description": "Clothing made of connected monster bones.",
        "special_effects": {
          "Absb": [
            "Dark"
          ]
        },
        "viera_only": false
      },
      {
        "name": "Onlyone",
        "jobs": [
          "Soldier",
          "Fighter",
          "Thief",
          "Ninja",
          "White Mage",
          "Black Mage",
          "IllusionistBlue Mage Archer",
          "Hunter",
          "Warrior",
          "Gladiator",
          "White Monk",
          "Bishop",
          "Templar",
          "Time Mage",
          "Alchemist",
          "Beastmaster",
          "Morpher",
          "Sage",
          "Fencer",
          "Elementalist",
          "Red Mage",
          "Summoner",
          "Assassain",
          "Sniper",
          "Animist",
          "Gunner",
          "Juggler",
          "Gadgeteer"
        ],
        "element": "None",
        "WpnATK": 0,
        "WpnDEF": 34,
        "MagPOW": 0,
        "MagRES": 24,
        "Speed": 0,
        "Move": 0,
        "Jump": 0,
        "Evade": 0,
        "description": "Sturdy tunic. The only clothes you'll ever need.",
        "special_effects": null,
        "viera_only": false
      },
      {
        "name": "Brint Set",
        "jobs": [
          "Soldier",
          "Fighter",
          "Thief",
          "Ninja",
          "White Mage",
          "Black Mage",
          "IllusionistBlue Mage Archer",
          "Hunter",
          "Warrior",
          "Gladiator",
          "White Monk",
          "Bishop",
          "Templar",
          "Time Mage",
          "Alchemist",
          "Beastmaster",
          "Morpher",
          "Sage",
          "Fencer",
          "Elementalist",
          "Red Mage",
          "Summoner",
          "Assassain",
          "Sniper",
          "Animist",
          "Gunner",
          "Juggler",
          "Gadgeteer"
        ],
        "element": "None",
        "WpnATK": 0,
        "WpnDEF": 28,
        "MagPOW": 0,
        "MagRES": 16,
        "Speed": 0,
        "Move": 0,
        "Jump": 0,
        "Evade": 0,
        "description": "The latest from famed designer \"Brint.\"",
        "special_effects": null,
        "viera_only": false
      },
      {
        "name": "Galmia Set",
        "jobs": [
          "Soldier",
          "Fighter",
          "Thief",
          "Ninja",
          "White Mage",
          "Black Mage",
          "IllusionistBlue Mage Archer",
          "Hunter",
          "Warrior",
          "Gladiator",
          "White Monk",
          "Bishop",
          "Templar",
          "Time Mage",
          "Alchemist",
          "Beastmaster",
          "Morpher",
          "Sage",
          "Fencer",
          "Elementalist",
          "Red Mage",
          "Summoner",
          "Assassain",
          "Sniper",
          "Animist",
          "Gunner",
          "Juggler",
          "Gadgeteer"
        ],
        "element": "None",
        "WpnATK": 0,
        "WpnDEF": 26,
        "MagPOW": 0,
        "MagRES": 18,
        "Speed": 0,
        "Move": 0,
        "Jump": 0,
        "Evade": 0,
        "description": "Galmia's latest creation. Uses lavish chocobo hides.",
        "special_effects": null,
        "viera_only": false
      },
      {
        "name": "Judge Coat",
        "jobs": [
          "Soldier",
          "Fighter",
          "Thief",
          "Ninja",
          "White Mage",
          "Black Mage",
          "IllusionistBlue Mage Archer",
          "Hunter",
          "Warrior",
          "Gladiator",
          "White Monk",
          "Bishop",
          "Templar",
          "Time Mage",
          "Alchemist",
          "Beastmaster",
          "Morpher",
          "Sage",
          "Fencer",
          "Elementalist",
          "Red Mage",
          "Summoner",
          "Assassain",
          "Sniper",
          "Animist",
          "Gunner",
          "Juggler",
          "Gadgeteer"
        ],
        "element": "None",
        "WpnATK": 0,
        "WpnDEF": 38,
        "MagPOW": 0,
        "MagRES": 28,
        "Speed": 0,
        "Move": 0,
        "Jump": 0,
        "Evade": 0,
        "description": "Every kid in Ivalice wants one of these judge coats.",
        "special_effects": null,
        "viera_only": false
      },
      {
        "name": "Temple Cloth",
        "jobs": [
          "Soldier",
          "Fighter",
          "Thief",
          "Ninja",
          "White Mage",
          "Black Mage",
          "IllusionistBlue Mage Archer",
          "Hunter",
          "Warrior",
          "Gladiator",
          "White Monk",
          "Bishop",
          "Templar",
          "Time Mage",
          "Alchemist",
          "Beastmaster",
          "Morpher",
          "Sage",
          "Fencer",
          "Elementalist",
          "Red Mage",
          "Summoner",
          "Assassain",
          "Sniper",
          "Animist",
          "Gunner",
          "Juggler",
          "Gadgeteer"
        ],
        "element": "None",
        "WpnATK": 2,
        "WpnDEF": 36,
        "MagPOW": 2,
        "MagRES": 16,
        "Speed": 0,
        "Move": 0,
        "Jump": 0,
        "Evade": 0,
        "description": "Uniform of a long-gone order of knights.",
        "special_effects": null,
        "viera_only": false
      },
      {
        "name": "Minerva Plate",
        "jobs": [
          "Fencer",
          "Elementalist",
          "Red Mage",
          "White Mage",
          "Summoner",
          "Archer",
          "Assassain",
          "Sniper"
        ],
        "element": "None",
        "WpnATK": 0,
        "WpnDEF": 28,
        "MagPOW": 0,
        "MagRES": 14,
        "Speed": 0,
        "Move": 0,
        "Jump": 0,
        "Evade": 0,
        "description": "Women's clothes worn by the goddess of victory.",
        "special_effects": {
          "Null": [
            "Dark"
          ]
        },
        "viera_only": true
      },
      {
        "name": "Rubber Suit",
        "jobs": [
          "Fencer",
          "Elementalist",
          "Red Mage",
          "White Mage",
          "Summoner",
          "Archer",
          "Assassain",
          "Sniper"
        ],
        "element": "None",
        "WpnATK": 0,
        "WpnDEF": 28,
        "MagPOW": 0,
        "MagRES": 16,
        "Speed": 0,
        "Move": 0,
        "Jump": 0,
        "Evade": 0,
        "description": "Women's insulated clothing.",
        "special_effects": {
          "Null": [
            "Lightning"
          ]
        },
        "viera_only": true
      }
    ],
    "robes": [
      {
        "name": "Hempen Robe",
        "jobs": [
          "Paladin",
          "White Mage",
          "Black Mage",
          "Illusionist",
          "Blue Mage",
          "Defender",
          "Bishop",
          "Templar",
          "Time Mage",
          "Morpher",
          "Sage",
          "Elementalist",
          "Red Mage",
          "Summoner"
        ],
        "element": "None",
        "WpnATK": 0,
        "WpnDEF": 15,
        "MagPOW": 0,
        "MagRES": 22,
        "Speed": 0,
        "Move": 0,
        "Jump": 0,
        "Evade": 0,
        "description": "Simple, hempen robe.",
        "special_effects": null,
        "viera_only": false
      },
      {
        "name": "Silken Robe",
        "jobs": [
          "Paladin",
          "White Mage",
          "Black Mage",
          "Illusionist",
          "Blue Mage",
          "Defender",
          "Bishop",
          "Templar",
          "Time Mage",
          "Morpher",
          "Sage",
          "Elementalist",
          "Red Mage",
          "Summoner"
        ],
        "element": "None",
        "WpnATK": 0,
        "WpnDEF": 15,
        "MagPOW": 0,
        "MagRES": 28,
        "Speed": 0,
        "Move": 0,
        "Jump": 0,
        "Evade": 0,
        "description": "Smooth robe made of the finest silk.",
        "special_effects": null,
        "viera_only": false
      },
      {
        "name": "Magus Robe",
        "jobs": [
          "Paladin",
          "White Mage",
          "Black Mage",
          "Illusionist",
          "Blue Mage",
          "Defender",
          "Bishop",
          "Templar",
          "Time Mage",
          "Morpher",
          "Sage",
          "Elementalist",
          "Red Mage",
          "Summoner"
        ],
        "element": "None",
        "WpnATK": 0,
        "WpnDEF": 15,
        "MagPOW": 0,
        "MagRES": 30,
        "Speed": 0,
        "Move": 0,
        "Jump": 0,
        "Evade": 0,
        "description": "Hooded robe favored by mages.",
        "special_effects": null,
        "viera_only": false
      },
      {
        "name": "Mistle Robe",
        "jobs": [
          "Paladin",
          "White Mage",
          "Black Mage",
          "Illusionist",
          "Blue Mage",
          "Defender",
          "Bishop",
          "Templar",
          "Time Mage",
          "Morpher",
          "Sage",
          "Elementalist",
          "Red Mage",
          "Summoner"
        ],
        "element": "Holy",
        "WpnATK": 0,
        "WpnDEF": 19,
        "MagPOW": 0,
        "MagRES": 30,
        "Speed": 0,
        "Move": 0,
        "Jump": 0,
        "Evade": 0,
        "description": "Good-luck robe dyed with mistletoe juice.",
        "special_effects": {
          "Absb": [
            "Holy"
          ],
          "Null": [
            "KO"
          ]
        },
        "viera_only": false
      },
      {
        "name": "Blaze Robe",
        "jobs": [
          "Paladin",
          "White Mage",
          "Black Mage",
          "Illusionist",
          "Blue Mage",
          "Defender",
          "Bishop",
          "Templar",
          "Time Mage",
          "Morpher",
          "Sage",
          "Elementalist",
          "Red Mage",
          "Summoner"
        ],
        "element": "Fire",
        "WpnATK": 0,
        "WpnDEF": 19,
        "MagPOW": 0,
        "MagRES": 30,
        "Speed": 0,
        "Move": 0,
        "Jump": 0,
        "Evade": 0,
        "description": "This robe would not burn in the middle of a fire.",
        "special_effects": {
          "Absb": [
            "Fire"
          ]
        },
        "viera_only": false
      },
      {
        "name": "Thunder Robe",
        "jobs": [
          "Paladin",
          "White Mage",
          "Black Mage",
          "Illusionist",
          "Blue Mage",
          "Defender",
          "Bishop",
          "Templar",
          "Time Mage",
          "Morpher",
          "Sage",
          "Elementalist",
          "Red Mage",
          "Summoner"
        ],
        "element": "Lightning",
        "WpnATK": 0,
        "WpnDEF": 19,
        "MagPOW": 0,
        "MagRES": 30,
        "Speed": 0,
        "Move": 0,
        "Jump": 0,
        "Evade": 0,
        "description": "This robe turn lightning into power for its wearer.",
        "special_effects": {
          "Absb": [
            "Lightning"
          ]
        },
        "viera_only": false
      },
      {
        "name": "Flurry Robe",
        "jobs": [
          "Paladin",
          "White Mage",
          "Black Mage",
          "Illusionist",
          "Blue Mage",
          "Defender",
          "Bishop",
          "Templar",
          "Time Mage",
          "Morpher",
          "Sage",
          "Elementalist",
          "Red Mage",
          "Summoner"
        ],
        "element": "Ice",
        "WpnATK": 0,
        "WpnDEF": 19,
        "MagPOW": 0,
        "MagRES": 30,
        "Speed": 0,
        "Move": 0,
        "Jump": 0,
        "Evade": 0,
        "description": "Robe woven with a slow flurry.",
        "special_effects": {
          "Absb": [
            "Ice"
          ]
        },
        "viera_only": false
      },
      {
        "name": "White Robe",
        "jobs": [
          "Paladin",
          "White Mage",
          "Black Mage",
          "Illusionist",
          "Blue Mage",
          "Defender",
          "Bishop",
          "Templar",
          "Time Mage",
          "Morpher",
          "Sage",
          "Elementalist",
          "Red Mage",
          "Summoner"
        ],
        "element": "None",
        "WpnATK": 0,
        "WpnDEF": 21,
        "MagPOW": 0,
        "MagRES": 38,
        "Speed": 0,
        "Move": 0,
        "Jump": 0,
        "Evade": 0,
        "description": "Pure white robe that protects from black magic.",
        "special_effects": {
          "Half": [
            "Fire",
            "Lightning",
            "Ice"
          ]
        },
        "viera_only": false
      },
      {
        "name": "Black Robe",
        "jobs": [
          "Paladin",
          "White Mage",
          "Black Mage",
          "Illusionist",
          "Blue Mage",
          "Defender",
          "Bishop",
          "Templar",
          "Time Mage",
          "Morpher",
          "Sage",
          "Elementalist",
          "Red Mage",
          "Summoner"
        ],
        "element": "None",
        "WpnATK": 0,
        "WpnDEF": 21,
        "MagPOW": 2,
        "MagRES": 36,
        "Speed": 0,
        "Move": 0,
        "Jump": 0,
        "Evade": 0,
        "description": "Lacquer-hued robe that strengthens black magic.",
        "special_effects": {
          "Enhn": [
            "Fire",
            "Lightning",
            "Ice"
          ]
        },
        "viera_only": false
      },
      {
        "name": "Light Robe",
        "jobs": [
          "Paladin",
          "White Mage",
          "Black Mage",
          "Illusionist",
          "Blue Mage",
          "Defender",
          "Bishop",
          "Templar",
          "Time Mage",
          "Morpher",
          "Sage",
          "Elementalist",
          "Red Mage",
          "Summoner"
        ],
        "element": "None",
        "WpnATK": 0,
        "WpnDEF": 25,
        "MagPOW": 0,
        "MagRES": 40,
        "Speed": 0,
        "Move": 0,
        "Jump": 0,
        "Evade": 0,
        "description": "This beautiful robe prevents exhaustion.",
        "special_effects": null,
        "viera_only": false
      },
      {
        "name": "Lordly Robe",
        "jobs": [
          "Paladin",
          "White Mage",
          "Black Mage",
          "Illusionist",
          "Blue Mage",
          "Defender",
          "Bishop",
          "Templar",
          "Time Mage",
          "Morpher",
          "Sage",
          "Elementalist",
          "Red Mage",
          "Summoner"
        ],
        "element": "None",
        "WpnATK": 0,
        "WpnDEF": 28,
        "MagPOW": 0,
        "MagRES": 42,
        "Speed": 0,
        "Move": 0,
        "Jump": 0,
        "Evade": 0,
        "description": "Robes worn by all the leaders of old.",
        "special_effects": null,
        "viera_only": false
      },
      {
        "name": "Silver Coat",
        "jobs": [
          "Paladin",
          "White Mage",
          "Black Mage",
          "Illusionist",
          "Blue Mage",
          "Defender",
          "Bishop",
          "Templar",
          "Time Mage",
          "Morpher",
          "Sage",
          "Elementalist",
          "Red Mage",
          "Summoner"
        ],
        "element": "None",
        "WpnATK": 0,
        "WpnDEF": 30,
        "MagPOW": 0,
        "MagRES": 38,
        "Speed": 0,
        "Move": 0,
        "Jump": 0,
        "Evade": 0,
        "description": "This coat has a mystical silvery shimmer.",
        "special_effects": null,
        "viera_only": false
      },
      {
        "name": "Red Robe",
        "jobs": [
          "Paladin",
          "White Mage",
          "Black Mage",
          "Illusionist",
          "Blue Mage",
          "Defender",
          "Bishop",
          "Templar",
          "Time Mage",
          "Morpher",
          "Sage",
          "Elementalist",
          "Red Mage",
          "Summoner"
        ],
        "element": "None",
        "WpnATK": 0,
        "WpnDEF": 22,
        "MagPOW": 0,
        "MagRES": 31,
        "Speed": 0,
        "Move": 0,
        "Jump": 0,
        "Evade": 0,
        "description": "Stylish robe made for red mages.",
        "special_effects": null,
        "viera_only": false
      },
      {
        "name": "Sage Robe",
        "jobs": [
          "Paladin",
          "White Mage",
          "Black Mage",
          "Illusionist",
          "Blue Mage",
          "Defender",
          "Bishop",
          "Templar",
          "Time Mage",
          "Morpher",
          "Sage",
          "Elementalist",
          "Red Mage",
          "Summoner"
        ],
        "element": "None",
        "WpnATK": 0,
        "WpnDEF": 24,
        "MagPOW": 0,
        "MagRES": 52,
        "Speed": 0,
        "Move": 0,
        "Jump": 0,
        "Evade": 0,
        "description": "Soft Cloth robe given to accomplished sages.",
        "special_effects": null,
        "viera_only": false
      },
      {
        "name": "Magic Robe",
        "jobs": [
          "Paladin",
          "White Mage",
          "Black Mage",
          "Illusionist",
          "Blue Mage",
          "Defender",
          "Bishop",
          "Templar",
          "Time Mage",
          "Morpher",
          "Sage",
          "Elementalist",
          "Red Mage",
          "Summoner"
        ],
        "element": "None",
        "WpnATK": 0,
        "WpnDEF": 24,
        "MagPOW": 6,
        "MagRES": 36,
        "Speed": 0,
        "Move": 0,
        "Jump": 0,
        "Evade": 0,
        "description": "Sky-colored robe only worn by the honest and humble.",
        "special_effects": null,
        "viera_only": false
      },
      {
        "name": "Reaper Cloak",
        "jobs": [
          "Paladin",
          "White Mage",
          "Black Mage",
          "Illusionist",
          "Blue Mage",
          "Defender",
          "Bishop",
          "Templar",
          "Time Mage",
          "Morpher",
          "Sage",
          "Elementalist",
          "Red Mage",
          "Summoner"
        ],
        "element": "Dark",
        "WpnATK": 0,
        "WpnDEF": 32,
        "MagPOW": 0,
        "MagRES": 36,
        "Speed": 0,
        "Move": 0,
        "Jump": 0,
        "Evade": 0,
        "description": "Robe stained black with blood.",
        "special_effects": null,
        "viera_only": false
      }
    ]
  },
  "accessories": {
    "shoes": [
      {
        "name": "Battle Shoes",
        "jobs": [],
        "element": "None",
        "WpnATK": 0,
        "WpnDEF": 7,
        "MagPOW": 0,
        "MagRES": 0,
        "Speed": 0,
        "Move": 0,
        "Jump": 0,
        "Evade": 0,
        "description": "Hard leather boots.",
        "special_effects": null,
        "viera_only": false
      },
      {
        "name": "Spiked Boots",
        "jobs": [],
        "element": "None",
        "WpnATK": 0,
        "WpnDEF": 4,
        "MagPOW": 0,
        "MagRES": 0,
        "Speed": 0,
        "Move": 0,
        "Jump": 1,
        "Evade": 0,
        "description": "Spiked shoes for better jumping.",
        "special_effects": null,
        "viera_only": false
      },
      {
        "name": "Dash Shoes",
        "jobs": [],
        "element": "None",
        "WpnATK": 0,
        "WpnDEF": 2,
        "MagPOW": 0,
        "MagRES": 0,
        "Speed": 0,
        "Move": 1,
        "Jump": 0,
        "Evade": 0,
        "description": "Speedy shoes for faster movement.",
        "special_effects": null,
        "viera_only": false
      },
      {
        "name": "Red Shoes",
        "jobs": [],
        "element": "None",
        "WpnATK": 0,
        "WpnDEF": 3,
        "MagPOW": 0,
        "MagRES": 5,
        "Speed": 0,
        "Move": 0,
        "Jump": 0,
        "Evade": 2,
        "description": "Red shoes dyed with medicinal herbs.",
        "special_effects": null,
        "viera_only": false
      },
      {
        "name": "Feather Boots",
        "jobs": [],
        "element": "None",
        "WpnATK": 0,
        "WpnDEF": 3,
        "MagPOW": 0,
        "MagRES": 0,
        "Speed": 0,
        "Move": 0,
        "Jump": 0,
        "Evade": 0,
        "description": "Feather boots. Their wearer can walk on water.",
        "special_effects": null,
        "viera_only": false
      },
      {
        "name": "Germinas",
        "jobs": [],
        "element": "None",
        "WpnATK": 0,
        "WpnDEF": 3,
        "MagPOW": 0,
        "MagRES": 0,
        "Speed": 0,
        "Move": 0,
        "Jump": 2,
        "Evade": 0,
        "description": "Sturdy boots for climbing. Greatly improves jumps.",
        "special_effects": null,
        "viera_only": false
      },
      {
        "name": "Caligula",
        "jobs": [],
        "element": "None",
        "WpnATK": 3,
        "WpnDEF": 10,
        "MagPOW": 0,
        "MagRES": 0,
        "Speed": 0,
        "Move": 0,
        "Jump": 0,
        "Evade": 0,
        "description": "Boots worn by royal guards in the age of kings.",
        "special_effects": null,
        "viera_only": false
      }
    ],
    "armlets": [
      {
        "name": "Gauntlets",
        "jobs": [],
        "element": "None",
        "WpnATK": 5,
        "WpnDEF": 5,
        "MagPOW": 0,
        "MagRES": 0,
        "Speed": 0,
        "Move": 0,
        "Jump": 0,
        "Evade": 0,
        "description": "Gloves that stretch form elbow to finger.",
        "special_effects": null,
        "viera_only": false
      },
      {
        "name": "Thief Armlets",
        "jobs": [],
        "element": "None",
        "WpnATK": 3,
        "WpnDEF": 3,
        "MagPOW": 0,
        "MagRES": 0,
        "Speed": 0,
        "Move": 0,
        "Jump": 0,
        "Evade": 0,
        "description": "Armlets made to allow maximum finger movement.",
        "special_effects": null,
        "viera_only": false
      },
      {
        "name": "Bracers",
        "jobs": [],
        "element": "None",
        "WpnATK": 5,
        "WpnDEF": 12,
        "MagPOW": 0,
        "MagRES": 0,
        "Speed": 0,
        "Move": 0,
        "Jump": 0,
        "Evade": 0,
        "description": "Leather bracers made so as not to hinder the hands.",
        "special_effects": null,
        "viera_only": false
      },
      {
        "name": "Genji Armlets",
        "jobs": [],
        "element": "None",
        "WpnATK": 5,
        "WpnDEF": 10,
        "MagPOW": 2,
        "MagRES": 5,
        "Speed": 0,
        "Move": 0,
        "Jump": 0,
        "Evade": 0,
        "description": "These colorful armlets are beautifully adorned.",
        "special_effects": null,
        "viera_only": false
      },
      {
        "name": "Fire Mitts",
        "jobs": [],
        "element": "None",
        "WpnATK": 0,
        "WpnDEF": 8,
        "MagPOW": 0,
        "MagRES": 10,
        "Speed": 0,
        "Move": 0,
        "Jump": 0,
        "Evade": 0,
        "description": "Specially fire-proofed gloves. Good pot holders.",
        "special_effects": {
          "Null": [
            "Fire"
          ]
        },
        "viera_only": false
      },
      {
        "name": "Bone Armlets",
        "jobs": [],
        "element": "None",
        "WpnATK": 3,
        "WpnDEF": 6,
        "MagPOW": 0,
        "MagRES": 8,
        "Speed": 0,
        "Move": 0,
        "Jump": 0,
        "Evade": 5,
        "description": "Armlets made of animal bone to ward off attacks.",
        "special_effects": null,
        "viera_only": false
      }
    ],
    "accessories": [
      {
        "name": "Fortune Ring",
        "jobs": [],
        "element": "None",
        "WpnATK": 0,
        "WpnDEF": 3,
        "MagPOW": 0,
        "MagRES": 5,
        "Speed": 0,
        "Move": 0,
        "Jump": 0,
        "Evade": 0,
        "description": "Ring set with a stone of power.",
        "special_effects": {
          "Null": [
            "Sleep",
            "Doom"
          ]
        },
        "viera_only": false
      },
      {
        "name": "Magic Ring",
        "jobs": [],
        "element": "None",
        "WpnATK": 0,
        "WpnDEF": 0,
        "MagPOW": 3,
        "MagRES": 10,
        "Speed": 0,
        "Move": 0,
        "Jump": 0,
        "Evade": 0,
        "description": "Ring engraved with magic-enhancing symbols.",
        "special_effects": null,
        "viera_only": false
      },
      {
        "name": "Angel Ring",
        "jobs": [],
        "element": "None",
        "WpnATK": 0,
        "WpnDEF": 0,
        "MagPOW": 0,
        "MagRES": 0,
        "Speed": 0,
        "Move": 0,
        "Jump": 0,
        "Evade": 0,
        "description": "Ring of blessing said to have been made by angels.",
        "special_effects": {
          "Null": [
            "Zombie",
            "Dark",
            "Silence",
            "Frog",
            "Poison",
            "Slow",
            "Immobilize",
            "Disarm",
            "Doom"
          ]
        },
        "viera_only": false
      },
      {
        "name": "Scarab",
        "jobs": [],
        "element": "None",
        "WpnATK": 0,
        "WpnDEF": 2,
        "MagPOW": 0,
        "MagRES": 8,
        "Speed": 0,
        "Move": 0,
        "Jump": 0,
        "Evade": 0,
        "description": "Scarab brooch that glitters like a rainbow.",
        "special_effects": {
          "Null": [
            "Immobilize",
            "Disarm",
            "Frog"
          ]
        },
        "viera_only": false
      },
      {
        "name": "Ruby Earring",
        "jobs": [],
        "element": "None",
        "WpnATK": 0,
        "WpnDEF": 3,
        "MagPOW": 0,
        "MagRES": 6,
        "Speed": 0,
        "Move": 0,
        "Jump": 0,
        "Evade": 0,
        "description": "Earrings with tear-shaped rubies.",
        "special_effects": {
          "Null": [
            "Confuse",
            "Charm"
          ],
          "Half": [
            "Dark"
          ]
        },
        "viera_only": false
      },
      {
        "name": "Star Armlet",
        "jobs": [],
        "element": "None",
        "WpnATK": 0,
        "WpnDEF": 4,
        "MagPOW": 6,
        "MagRES": 4,
        "Speed": 2,
        "Move": 0,
        "Jump": 0,
        "Evade": 0,
        "description": "Armband worn by a great diviner of old.",
        "special_effects": {
          "Null": [
            "Stop",
            "Slow"
          ]
        },
        "viera_only": false
      }
    ]
  }
}